{
    "id": 96182791,
    "name": "FLORAL STROBE",
    "author": "ImMaxX1",
    "creators": [],
    "verifier": "ImMaxX1",
    "verification": "https://youtu.be/QOmZDKSAS5I?si=dt8dpqvkEjfC3OQy",
    "percentToQualify": 100,
    "password": "Free to Copy",
    "records" : [
        {
            "user": "Fawxu",
            "link": "https://youtu.be/OIb1S9IGV7w?si=dZXt97SA5dzByFTk",
            "percent": 100,
            "hz": 240
    },
    {
        "user": "tomm",
        "link": "https://youtu.be/0wUJleNo2Ls",
        "percent": 100,
        "hz": 240
},
{
    "user": "JoacoPe",
    "link": "https://youtu.be/GZynIzaR9zA",
    "percent": 100,
    "hz": 120
},
        {
            "user": "lllSafeSpacelll",
            "link": "https://www.youtube.com/watch?v=eldxcw4YuIw",
            "percent": 100,
            "hz": 120
        },
        {
            "user": "Leven",
            "link": "https://youtu.be/Ln_i5qG2iC8",
            "percent": 100,
            "hz": 144
        },
        {
            "user": "Robaleg9",
            "link": "https://youtu.be/pTVgamzrcaQ",
            "percent": 100,
            "hz": 240
        }
    ]
}
